odoo/addons/dbfilter_from_header/README.rst
odoo/addons/dbfilter_from_header/__init__.py
odoo/addons/dbfilter_from_header/__manifest__.py
odoo/addons/dbfilter_from_header/override.py
odoo/addons/dbfilter_from_header/i18n/dbfilter_from_header.pot
odoo/addons/dbfilter_from_header/static/description/icon.png
odoo11_addon_dbfilter_from_header-11.0.1.0.0.dist-info/DESCRIPTION.rst
odoo11_addon_dbfilter_from_header-11.0.1.0.0.dist-info/METADATA
odoo11_addon_dbfilter_from_header-11.0.1.0.0.dist-info/RECORD
odoo11_addon_dbfilter_from_header-11.0.1.0.0.dist-info/WHEEL
odoo11_addon_dbfilter_from_header-11.0.1.0.0.dist-info/metadata.json
odoo11_addon_dbfilter_from_header-11.0.1.0.0.dist-info/top_level.txt
